{"textures":{"0":"modelengine:entity/shadowguardian","1":"modelengine:entity/shadowguardian_flame","particle":"#0"},"elements":[{"from":[6.725,-1.1576986,5.1913347],"to":[9.185,1.3023014,8.061335],"faces":{"east":{"uv":[5.875,10.125,6.625,10.75],"tintindex":0,"rotation":0,"texture":"#0"},"south":{"uv":[10.625,4.75,11.25,5.375],"tintindex":0,"rotation":0,"texture":"#0"},"north":{"uv":[10.625,4.125,11.25,4.75],"tintindex":0,"rotation":0,"texture":"#0"},"west":{"uv":[10.125,6.125,10.875,6.75],"tintindex":0,"rotation":0,"texture":"#0"},"up":{"uv":[10.875,1.375,10.25,0.625],"tintindex":0,"rotation":0,"texture":"#0"},"down":{"uv":[2.125,10.25,1.5,11.0],"tintindex":0,"rotation":0,"texture":"#0"}},"rotation":{"origin":[7.894659,0.8644743,7.3954678],"angle":-22.5,"axis":"x"}},{"from":[6.19,1.4793434,4.287019],"to":[9.8,4.759344,7.5670185],"faces":{"east":{"uv":[7.625,1.875,8.5,2.75],"tintindex":0,"rotation":0,"texture":"#0"},"south":{"uv":[3.125,7.625,4.0,8.5],"tintindex":0,"rotation":0,"texture":"#0"},"north":{"uv":[1.25,7.5,2.125,8.375],"tintindex":0,"rotation":0,"texture":"#0"},"west":{"uv":[7.625,6.25,8.5,7.125],"tintindex":0,"rotation":0,"texture":"#0"},"up":{"uv":[8.5,8.0,7.625,7.125],"tintindex":0,"rotation":0,"texture":"#0"},"down":{"uv":[3.0,7.75,2.125,8.625],"tintindex":0,"rotation":0,"texture":"#0"}},"rotation":{"origin":[7.894659,0.8644743,7.3954678],"angle":22.5,"axis":"x"}},{"from":[6.315,0.32499886,4.925],"to":[9.595,2.784999,7.795],"faces":{"east":{"uv":[0.0,10.125,0.75,10.75],"tintindex":0,"rotation":0,"texture":"#0"},"south":{"uv":[9.625,0.0,10.5,0.625],"tintindex":0,"rotation":0,"texture":"#0"},"north":{"uv":[0.0,9.5,0.875,10.125],"tintindex":0,"rotation":0,"texture":"#0"},"west":{"uv":[10.125,5.5,10.875,6.125],"tintindex":0,"rotation":0,"texture":"#0"},"up":{"uv":[7.125,9.375,6.25,8.625],"tintindex":0,"rotation":0,"texture":"#0"},"down":{"uv":[0.875,8.75,0.0,9.5],"tintindex":0,"rotation":0,"texture":"#0"}}},{"from":[8.08,-3.9954872,2.2297783],"to":[8.08,6.504513,22.229778],"faces":{"east":{"uv":[5.0,16.0,12.0,0.0],"tintindex":0,"rotation":270,"texture":"#1"},"west":{"uv":[5.0,0.0,12.0,16.0],"tintindex":0,"rotation":270,"texture":"#1"}},"rotation":{"origin":[7.894659,0.8644743,7.3954678],"angle":45.0,"axis":"x"}},{"from":[2.5904365,-12.84794,7.328642],"to":[12.090437,7.1520596,7.328642],"faces":{"south":{"uv":[5.0,16.0,12.0,0.0],"tintindex":0,"rotation":180,"texture":"#1"},"north":{"uv":[5.0,0.0,12.0,16.0],"tintindex":0,"rotation":0,"texture":"#1"}},"rotation":{"origin":[7.894659,0.8644743,7.3954678],"angle":-22.5,"axis":"x"}}],"display":{"head":{"rotation":[0.0,0.0,0.0]},"firstperson_righthand":{"rotation":[0.0,0.0,0.0]},"thirdperson_lefthand":{"rotation":[0.0,-0.0,-0.0]},"firstperson_lefthand":{"rotation":[0.0,-0.0,-0.0]},"fixed":{"rotation":[0.0,0.0,0.0]},"ground":{"rotation":[0.0,0.0,0.0]},"thirdperson_righthand":{"rotation":[0.0,0.0,0.0]},"gui":{"rotation":[-150.0,-45.0,180.0]}}}